{
  "technique": "trucking",
  "video_count": 120,
  "generated_at": "2025-09-09T09:01:36.265758",
  "videos": [
    {
      "video_url": "https://asset.eyecannndy.com/media/clip/2024/03/14/261710391333.webp",
      "page_url": "https://eyecannndy.com/technique/trucking",
      "discovered_at": "2025-09-09T08:56:27.556435",
      "element_tag": "img",
      "title": "Feid - ALAKRAN",
      "description": "",
      "category": "Technique",
      "alt_text": "Feid - ALAKRAN",
      "css_classes": "lazy-img lazyImages1 trigger_info_ show-it",
      "file_size": null,
      "dimensions": null,
      "tags": [
        "Eyecandy",
        "lazy img",
        "lazyImages1",
        "trigger_info_",
        "show it"
      ]
    },
    {
      "video_url": "https://asset.eyecannndy.com/media/clip/2024/03/16/261710577893.webp",
      "page_url": "https://eyecannndy.com/technique/trucking",
      "discovered_at": "2025-09-09T08:56:27.556512",
      "element_tag": "img",
      "title": "Busta Rhymes - BIG EVERYTHING",
      "description": "",
      "category": "Technique",
      "alt_text": "Busta Rhymes - BIG EVERYTHING",
      "css_classes": "lazy-img lazyImages1 trigger_info_ show-it",
      "file_size": null,
      "dimensions": null,
      "tags": [
        "Eyecandy",
        "lazy img",
        "lazyImages1",
        "trigger_info_",
        "show it"
      ]
    },
    {
      "video_url": "https://asset.eyecannndy.com/media/clip/2024/03/12/261710225240.webp",
      "page_url": "https://eyecannndy.com/technique/trucking",
      "discovered_at": "2025-09-09T08:56:27.556559",
      "element_tag": "img",
      "title": "The Gentlemen (TV Series)",
      "description": "",
      "category": "Technique",
      "alt_text": "The Gentlemen (TV Series)",
      "css_classes": "lazy-img lazyImages1 trigger_info_ show-it",
      "file_size": null,
      "dimensions": null,
      "tags": [
        "Eyecandy",
        "lazy img",
        "lazyImages1",
        "trigger_info_",
        "show it"
      ]
    },
    {
      "video_url": "https://asset.eyecannndy.com/media/clip/2024/03/25/261711342512.webp",
      "page_url": "https://eyecannndy.com/technique/trucking",
      "discovered_at": "2025-09-09T08:56:27.556602",
      "element_tag": "img",
      "title": "Fantastic Mr. Fox",
      "description": "",
      "category": "Technique",
      "alt_text": "Fantastic Mr. Fox",
      "css_classes": "lazy-img lazyImages1 trigger_info_ show-it",
      "file_size": null,
      "dimensions": null,
      "tags": [
        "Eyecandy",
        "lazy img",
        "lazyImages1",
        "trigger_info_",
        "show it"
      ]
    },
    {
      "video_url": "https://asset.eyecannndy.com/media/clip/2024/03/04/261709538123.webp",
      "page_url": "https://eyecannndy.com/technique/trucking",
      "discovered_at": "2025-09-09T08:56:27.556642",
      "element_tag": "img",
      "title": "Miel De Montagne - Le Pigeon",
      "description": "",
      "category": "Technique",
      "alt_text": "Miel De Montagne - Le Pigeon",
      "css_classes": "lazy-img lazyImages1 trigger_info_ show-it",
      "file_size": null,
      "dimensions": null,
      "tags": [
        "Eyecandy",
        "lazy img",
        "lazyImages1",
        "trigger_info_",
        "show it"
      ]
    },
    {
      "video_url": "https://asset.eyecannndy.com/media/clip/2024/05/09/261715292468.webp",
      "page_url": "https://eyecannndy.com/technique/trucking",
      "discovered_at": "2025-09-09T08:56:27.556679",
      "element_tag": "img",
      "title": "Inter Alia (Short Film)",
      "description": "",
      "category": "Technique",
      "alt_text": "Inter Alia (Short Film)",
      "css_classes": "lazy-img lazyImages1 trigger_info_ show-it",
      "file_size": null,
      "dimensions": null,
      "tags": [
        "Eyecandy",
        "lazy img",
        "lazyImages1",
        "trigger_info_",
        "show it"
      ]
    },
    {
      "video_url": "https://asset.eyecannndy.com/media/clip/2024/01/29/261706570246.webp",
      "page_url": "https://eyecannndy.com/technique/trucking",
      "discovered_at": "2025-09-09T08:56:27.556719",
      "element_tag": "img",
      "title": "Source unknown",
      "description": "",
      "category": "Technique",
      "alt_text": "Source unknown",
      "css_classes": "lazy-img lazyImages1 trigger_info_ show-it",
      "file_size": null,
      "dimensions": null,
      "tags": [
        "Eyecandy",
        "lazy img",
        "lazyImages1",
        "trigger_info_",
        "show it"
      ]
    },
    {
      "video_url": "https://asset.eyecannndy.com/media/clip/2024/03/24/261711258085.webp",
      "page_url": "https://eyecannndy.com/technique/trucking",
      "discovered_at": "2025-09-09T08:56:27.556756",
      "element_tag": "img",
      "title": "Sam Akpro - Death By Entertainment",
      "description": "",
      "category": "Technique",
      "alt_text": "Sam Akpro - Death By Entertainment",
      "css_classes": "lazy-img lazyImages1 trigger_info_ show-it",
      "file_size": null,
      "dimensions": null,
      "tags": [
        "Eyecandy",
        "lazy img",
        "lazyImages1",
        "trigger_info_",
        "show it"
      ]
    },
    {
      "video_url": "https://asset.eyecannndy.com/media/clip/2024/01/29/261706571438.webp",
      "page_url": "https://eyecannndy.com/technique/trucking",
      "discovered_at": "2025-09-09T08:56:27.556793",
      "element_tag": "img",
      "title": "Charlie's Angels",
      "description": "",
      "category": "Technique",
      "alt_text": "Charlie's Angels",
      "css_classes": "lazy-img lazyImages1 trigger_info_ show-it",
      "file_size": null,
      "dimensions": null,
      "tags": [
        "Eyecandy",
        "lazy img",
        "lazyImages1",
        "trigger_info_",
        "show it"
      ]
    },
    {
      "video_url": "https://asset.eyecannndy.com/media/clip/2024/01/29/261706567045.webp",
      "page_url": "https://eyecannndy.com/technique/trucking",
      "discovered_at": "2025-09-09T08:56:27.556830",
      "element_tag": "img",
      "title": "The Grand Budapest Hotel",
      "description": "",
      "category": "Technique",
      "alt_text": "The Grand Budapest Hotel",
      "css_classes": "lazy-img lazyImages1 trigger_info_ show-it",
      "file_size": null,
      "dimensions": null,
      "tags": [
        "Eyecandy",
        "lazy img",
        "lazyImages1",
        "trigger_info_",
        "show it"
      ]
    },
    {
      "video_url": "https://asset.eyecannndy.com/media/clip/2024/02/11/261707633657.webp",
      "page_url": "https://eyecannndy.com/technique/trucking",
      "discovered_at": "2025-09-09T08:56:27.556868",
      "element_tag": "img",
      "title": "IKEA – Show Off Your Savvy",
      "description": "",
      "category": "Technique",
      "alt_text": "IKEA – Show Off Your Savvy",
      "css_classes": "lazy-img lazyImages1 trigger_info_ show-it",
      "file_size": null,
      "dimensions": null,
      "tags": [
        "Eyecandy",
        "lazy img",
        "lazyImages1",
        "trigger_info_",
        "show it"
      ]
    },
    {
      "video_url": "https://asset.eyecannndy.com/media/clip/2024/07/05/261720163132.webp",
      "page_url": "https://eyecannndy.com/technique/trucking",
      "discovered_at": "2025-09-09T08:56:27.556905",
      "element_tag": "img",
      "title": "Bree Runway - Just Like That",
      "description": "",
      "category": "Technique",
      "alt_text": "Bree Runway - Just Like That",
      "css_classes": "lazy-img lazyImages1 trigger_info_ show-it",
      "file_size": null,
      "dimensions": null,
      "tags": [
        "Eyecandy",
        "lazy img",
        "lazyImages1",
        "trigger_info_",
        "show it"
      ]
    },
    {
      "video_url": "https://asset.eyecannndy.com/media/clip/2025/02/10/261739169383.webp",
      "page_url": "https://eyecannndy.com/technique/trucking",
      "discovered_at": "2025-09-09T08:56:27.556942",
      "element_tag": "img",
      "title": "GIVĒON - TWENTIES",
      "description": "",
      "category": "Technique",
      "alt_text": "GIVĒON - TWENTIES",
      "css_classes": "lazy-img lazyImages1 trigger_info_ show-it",
      "file_size": null,
      "dimensions": null,
      "tags": [
        "Eyecandy",
        "lazy img",
        "lazyImages1",
        "trigger_info_",
        "show it"
      ]
    },
    {
      "video_url": "https://asset.eyecannndy.com/media/clip/2024/03/25/261711342834.webp",
      "page_url": "https://eyecannndy.com/technique/trucking",
      "discovered_at": "2025-09-09T08:56:27.556979",
      "element_tag": "img",
      "title": "Fantastic Mr. Fox",
      "description": "",
      "category": "Technique",
      "alt_text": "Fantastic Mr. Fox",
      "css_classes": "lazy-img lazyImages1 trigger_info_ show-it",
      "file_size": null,
      "dimensions": null,
      "tags": [
        "Eyecandy",
        "lazy img",
        "lazyImages1",
        "trigger_info_",
        "show it"
      ]
    },
    {
      "video_url": "https://asset.eyecannndy.com/media/clip/2024/01/12/261705100311.webp",
      "page_url": "https://eyecannndy.com/technique/trucking",
      "discovered_at": "2025-09-09T08:56:27.557017",
      "element_tag": "img",
      "title": "A$AP Rocky - A$AP Forever",
      "description": "",
      "category": "Technique",
      "alt_text": "A$AP Rocky - A$AP Forever",
      "css_classes": "lazy-img lazyImages1 trigger_info_ show-it",
      "file_size": null,
      "dimensions": null,
      "tags": [
        "Eyecandy",
        "lazy img",
        "lazyImages1",
        "trigger_info_",
        "show it"
      ]
    },
    {
      "video_url": "https://asset.eyecannndy.com/media/clip/2023/12/19/261702958734.webp",
      "page_url": "https://eyecannndy.com/technique/trucking",
      "discovered_at": "2025-09-09T08:56:27.557053",
      "element_tag": "img",
      "title": "Axe - Monday",
      "description": "",
      "category": "Technique",
      "alt_text": "Axe - Monday",
      "css_classes": "lazy-img lazyImages1 trigger_info_ show-it",
      "file_size": null,
      "dimensions": null,
      "tags": [
        "Eyecandy",
        "lazy img",
        "lazyImages1",
        "trigger_info_",
        "show it"
      ]
    },
    {
      "video_url": "https://asset.eyecannndy.com/media/clip/2024/03/14/261710391333.webp",
      "page_url": "https://eyecannndy.com/technique/trucking",
      "discovered_at": "2025-09-09T08:56:27.557088",
      "element_tag": "img",
      "title": "Feid - ALAKRAN",
      "description": "",
      "category": "Technique",
      "alt_text": "Feid - ALAKRAN",
      "css_classes": "lazy-img lazyImages1 trigger_info_ show-it",
      "file_size": null,
      "dimensions": null,
      "tags": [
        "Eyecandy",
        "lazy img",
        "lazyImages1",
        "trigger_info_",
        "show it"
      ]
    },
    {
      "video_url": "https://asset.eyecannndy.com/media/clip/2024/03/16/261710577893.webp",
      "page_url": "https://eyecannndy.com/technique/trucking",
      "discovered_at": "2025-09-09T08:56:27.557124",
      "element_tag": "img",
      "title": "Busta Rhymes - BIG EVERYTHING",
      "description": "",
      "category": "Technique",
      "alt_text": "Busta Rhymes - BIG EVERYTHING",
      "css_classes": "lazy-img lazyImages1 trigger_info_ show-it",
      "file_size": null,
      "dimensions": null,
      "tags": [
        "Eyecandy",
        "lazy img",
        "lazyImages1",
        "trigger_info_",
        "show it"
      ]
    },
    {
      "video_url": "https://asset.eyecannndy.com/media/clip/2024/03/12/261710225240.webp",
      "page_url": "https://eyecannndy.com/technique/trucking",
      "discovered_at": "2025-09-09T08:56:27.557158",
      "element_tag": "img",
      "title": "The Gentlemen (TV Series)",
      "description": "",
      "category": "Technique",
      "alt_text": "The Gentlemen (TV Series)",
      "css_classes": "lazy-img lazyImages1 trigger_info_ show-it",
      "file_size": null,
      "dimensions": null,
      "tags": [
        "Eyecandy",
        "lazy img",
        "lazyImages1",
        "trigger_info_",
        "show it"
      ]
    },
    {
      "video_url": "https://asset.eyecannndy.com/media/clip/2024/03/25/261711342512.webp",
      "page_url": "https://eyecannndy.com/technique/trucking",
      "discovered_at": "2025-09-09T08:56:27.557192",
      "element_tag": "img",
      "title": "Fantastic Mr. Fox",
      "description": "",
      "category": "Technique",
      "alt_text": "Fantastic Mr. Fox",
      "css_classes": "lazy-img lazyImages1 trigger_info_ show-it",
      "file_size": null,
      "dimensions": null,
      "tags": [
        "Eyecandy",
        "lazy img",
        "lazyImages1",
        "trigger_info_",
        "show it"
      ]
    },
    {
      "video_url": "https://asset.eyecannndy.com/media/clip/2024/03/04/261709538123.webp",
      "page_url": "https://eyecannndy.com/technique/trucking",
      "discovered_at": "2025-09-09T08:56:27.557227",
      "element_tag": "img",
      "title": "Miel De Montagne - Le Pigeon",
      "description": "",
      "category": "Technique",
      "alt_text": "Miel De Montagne - Le Pigeon",
      "css_classes": "lazy-img lazyImages1 trigger_info_ show-it",
      "file_size": null,
      "dimensions": null,
      "tags": [
        "Eyecandy",
        "lazy img",
        "lazyImages1",
        "trigger_info_",
        "show it"
      ]
    },
    {
      "video_url": "https://asset.eyecannndy.com/media/clip/2024/05/09/261715292468.webp",
      "page_url": "https://eyecannndy.com/technique/trucking",
      "discovered_at": "2025-09-09T08:56:27.557261",
      "element_tag": "img",
      "title": "Inter Alia (Short Film)",
      "description": "",
      "category": "Technique",
      "alt_text": "Inter Alia (Short Film)",
      "css_classes": "lazy-img lazyImages1 trigger_info_ show-it",
      "file_size": null,
      "dimensions": null,
      "tags": [
        "Eyecandy",
        "lazy img",
        "lazyImages1",
        "trigger_info_",
        "show it"
      ]
    },
    {
      "video_url": "https://asset.eyecannndy.com/media/clip/2024/01/29/261706570246.webp",
      "page_url": "https://eyecannndy.com/technique/trucking",
      "discovered_at": "2025-09-09T08:56:27.557295",
      "element_tag": "img",
      "title": "Source unknown",
      "description": "",
      "category": "Technique",
      "alt_text": "Source unknown",
      "css_classes": "lazy-img lazyImages1 trigger_info_ show-it",
      "file_size": null,
      "dimensions": null,
      "tags": [
        "Eyecandy",
        "lazy img",
        "lazyImages1",
        "trigger_info_",
        "show it"
      ]
    },
    {
      "video_url": "https://asset.eyecannndy.com/media/clip/2024/03/24/261711258085.webp",
      "page_url": "https://eyecannndy.com/technique/trucking",
      "discovered_at": "2025-09-09T08:56:27.557327",
      "element_tag": "img",
      "title": "Sam Akpro - Death By Entertainment",
      "description": "",
      "category": "Technique",
      "alt_text": "Sam Akpro - Death By Entertainment",
      "css_classes": "lazy-img lazyImages1 trigger_info_ show-it",
      "file_size": null,
      "dimensions": null,
      "tags": [
        "Eyecandy",
        "lazy img",
        "lazyImages1",
        "trigger_info_",
        "show it"
      ]
    },
    {
      "video_url": "https://asset.eyecannndy.com/media/clip/2024/01/29/261706571438.webp",
      "page_url": "https://eyecannndy.com/technique/trucking",
      "discovered_at": "2025-09-09T08:56:27.557360",
      "element_tag": "img",
      "title": "Charlie's Angels",
      "description": "",
      "category": "Technique",
      "alt_text": "Charlie's Angels",
      "css_classes": "lazy-img lazyImages1 trigger_info_ show-it",
      "file_size": null,
      "dimensions": null,
      "tags": [
        "Eyecandy",
        "lazy img",
        "lazyImages1",
        "trigger_info_",
        "show it"
      ]
    },
    {
      "video_url": "https://asset.eyecannndy.com/media/clip/2024/01/29/261706567045.webp",
      "page_url": "https://eyecannndy.com/technique/trucking",
      "discovered_at": "2025-09-09T08:56:27.557392",
      "element_tag": "img",
      "title": "The Grand Budapest Hotel",
      "description": "",
      "category": "Technique",
      "alt_text": "The Grand Budapest Hotel",
      "css_classes": "lazy-img lazyImages1 trigger_info_ show-it",
      "file_size": null,
      "dimensions": null,
      "tags": [
        "Eyecandy",
        "lazy img",
        "lazyImages1",
        "trigger_info_",
        "show it"
      ]
    },
    {
      "video_url": "https://asset.eyecannndy.com/media/clip/2024/02/11/261707633657.webp",
      "page_url": "https://eyecannndy.com/technique/trucking",
      "discovered_at": "2025-09-09T08:56:27.557425",
      "element_tag": "img",
      "title": "IKEA – Show Off Your Savvy",
      "description": "",
      "category": "Technique",
      "alt_text": "IKEA – Show Off Your Savvy",
      "css_classes": "lazy-img lazyImages1 trigger_info_ show-it",
      "file_size": null,
      "dimensions": null,
      "tags": [
        "Eyecandy",
        "lazy img",
        "lazyImages1",
        "trigger_info_",
        "show it"
      ]
    },
    {
      "video_url": "https://asset.eyecannndy.com/media/clip/2024/07/05/261720163132.webp",
      "page_url": "https://eyecannndy.com/technique/trucking",
      "discovered_at": "2025-09-09T08:56:27.557457",
      "element_tag": "img",
      "title": "Bree Runway - Just Like That",
      "description": "",
      "category": "Technique",
      "alt_text": "Bree Runway - Just Like That",
      "css_classes": "lazy-img lazyImages1 trigger_info_ show-it",
      "file_size": null,
      "dimensions": null,
      "tags": [
        "Eyecandy",
        "lazy img",
        "lazyImages1",
        "trigger_info_",
        "show it"
      ]
    },
    {
      "video_url": "https://asset.eyecannndy.com/media/clip/2025/02/10/261739169383.webp",
      "page_url": "https://eyecannndy.com/technique/trucking",
      "discovered_at": "2025-09-09T08:56:27.557490",
      "element_tag": "img",
      "title": "GIVĒON - TWENTIES",
      "description": "",
      "category": "Technique",
      "alt_text": "GIVĒON - TWENTIES",
      "css_classes": "lazy-img lazyImages1 trigger_info_ show-it",
      "file_size": null,
      "dimensions": null,
      "tags": [
        "Eyecandy",
        "lazy img",
        "lazyImages1",
        "trigger_info_",
        "show it"
      ]
    },
    {
      "video_url": "https://asset.eyecannndy.com/media/clip/2024/03/25/261711342834.webp",
      "page_url": "https://eyecannndy.com/technique/trucking",
      "discovered_at": "2025-09-09T08:56:27.557523",
      "element_tag": "img",
      "title": "Fantastic Mr. Fox",
      "description": "",
      "category": "Technique",
      "alt_text": "Fantastic Mr. Fox",
      "css_classes": "lazy-img lazyImages1 trigger_info_ show-it",
      "file_size": null,
      "dimensions": null,
      "tags": [
        "Eyecandy",
        "lazy img",
        "lazyImages1",
        "trigger_info_",
        "show it"
      ]
    },
    {
      "video_url": "https://asset.eyecannndy.com/media/clip/2024/01/12/261705100311.webp",
      "page_url": "https://eyecannndy.com/technique/trucking",
      "discovered_at": "2025-09-09T08:56:27.557555",
      "element_tag": "img",
      "title": "A$AP Rocky - A$AP Forever",
      "description": "",
      "category": "Technique",
      "alt_text": "A$AP Rocky - A$AP Forever",
      "css_classes": "lazy-img lazyImages1 trigger_info_ show-it",
      "file_size": null,
      "dimensions": null,
      "tags": [
        "Eyecandy",
        "lazy img",
        "lazyImages1",
        "trigger_info_",
        "show it"
      ]
    },
    {
      "video_url": "https://asset.eyecannndy.com/media/clip/2023/12/19/261702958734.webp",
      "page_url": "https://eyecannndy.com/technique/trucking",
      "discovered_at": "2025-09-09T08:56:27.557588",
      "element_tag": "img",
      "title": "Axe - Monday",
      "description": "",
      "category": "Technique",
      "alt_text": "Axe - Monday",
      "css_classes": "lazy-img lazyImages1 trigger_info_ show-it",
      "file_size": null,
      "dimensions": null,
      "tags": [
        "Eyecandy",
        "lazy img",
        "lazyImages1",
        "trigger_info_",
        "show it"
      ]
    },
    {
      "video_url": "https://asset.eyecannndy.com/media/clip/2023/12/19/261702955612.webp",
      "page_url": "https://eyecannndy.com/technique/trucking",
      "discovered_at": "2025-09-09T08:56:27.557624",
      "element_tag": "img",
      "title": "Spirited Away",
      "description": "",
      "category": "Technique",
      "alt_text": "Spirited Away",
      "css_classes": "lazy-img lazyImages1 trigger_info_",
      "file_size": null,
      "dimensions": null,
      "tags": [
        "Eyecandy",
        "lazy img",
        "trigger_info_",
        "lazyImages1"
      ]
    },
    {
      "video_url": "https://asset.eyecannndy.com/media/clip/2024/03/13/261710315985.webp",
      "page_url": "https://eyecannndy.com/technique/trucking",
      "discovered_at": "2025-09-09T08:56:27.557662",
      "element_tag": "img",
      "title": "The Gentlemen (TV Series)",
      "description": "",
      "category": "Technique",
      "alt_text": "The Gentlemen (TV Series)",
      "css_classes": "lazy-img lazyImages1 trigger_info_",
      "file_size": null,
      "dimensions": null,
      "tags": [
        "Eyecandy",
        "lazy img",
        "trigger_info_",
        "lazyImages1"
      ]
    },
    {
      "video_url": "https://asset.eyecannndy.com/media/clip/2024/03/24/261711254274.webp",
      "page_url": "https://eyecannndy.com/technique/trucking",
      "discovered_at": "2025-09-09T08:56:27.557701",
      "element_tag": "img",
      "title": "Coach - Life Has Different Paths",
      "description": "",
      "category": "Technique",
      "alt_text": "Coach - Life Has Different Paths",
      "css_classes": "lazy-img lazyImages1 trigger_info_",
      "file_size": null,
      "dimensions": null,
      "tags": [
        "Eyecandy",
        "lazy img",
        "trigger_info_",
        "lazyImages1"
      ]
    },
    {
      "video_url": "https://asset.eyecannndy.com/media/clip/2023/12/24/261703400658.webp",
      "page_url": "https://eyecannndy.com/technique/trucking",
      "discovered_at": "2025-09-09T08:56:27.557742",
      "element_tag": "img",
      "title": "adidas Originals - Original Is Never Finished",
      "description": "",
      "category": "Technique",
      "alt_text": "adidas Originals - Original Is Never Finished",
      "css_classes": "lazy-img lazyImages1 trigger_info_",
      "file_size": null,
      "dimensions": null,
      "tags": [
        "Eyecandy",
        "lazy img",
        "trigger_info_",
        "lazyImages1"
      ]
    },
    {
      "video_url": "https://asset.eyecannndy.com/media/clip/2023/12/24/261703399872.webp",
      "page_url": "https://eyecannndy.com/technique/trucking",
      "discovered_at": "2025-09-09T08:56:27.557781",
      "element_tag": "img",
      "title": "adidas Originals - Original Is Never Finished",
      "description": "",
      "category": "Technique",
      "alt_text": "adidas Originals - Original Is Never Finished",
      "css_classes": "lazy-img lazyImages1 trigger_info_",
      "file_size": null,
      "dimensions": null,
      "tags": [
        "Eyecandy",
        "lazy img",
        "trigger_info_",
        "lazyImages1"
      ]
    },
    {
      "video_url": "https://asset.eyecannndy.com/media/clip/2024/02/27/261709017265.webp",
      "page_url": "https://eyecannndy.com/technique/trucking",
      "discovered_at": "2025-09-09T08:56:27.557819",
      "element_tag": "img",
      "title": "Sheck Wes, JID & Ski Mask The Slump God - Fly Away",
      "description": "",
      "category": "Technique",
      "alt_text": "Sheck Wes, JID & Ski Mask The Slump God - Fly Away",
      "css_classes": "lazy-img lazyImages1 trigger_info_",
      "file_size": null,
      "dimensions": null,
      "tags": [
        "Eyecandy",
        "lazy img",
        "trigger_info_",
        "lazyImages1"
      ]
    },
    {
      "video_url": "https://asset.eyecannndy.com/media/clip/2024/01/13/261705111256.webp",
      "page_url": "https://eyecannndy.com/technique/trucking",
      "discovered_at": "2025-09-09T08:56:27.557858",
      "element_tag": "img",
      "title": "Atlanta | Season 2: Spotlight Preview",
      "description": "",
      "category": "Technique",
      "alt_text": "Atlanta | Season 2: Spotlight Preview",
      "css_classes": "lazy-img lazyImages1 trigger_info_",
      "file_size": null,
      "dimensions": null,
      "tags": [
        "Eyecandy",
        "lazy img",
        "trigger_info_",
        "lazyImages1"
      ]
    },
    {
      "video_url": "https://asset.eyecannndy.com/media/clip/2024/01/29/261706566184.webp",
      "page_url": "https://eyecannndy.com/technique/trucking",
      "discovered_at": "2025-09-09T08:56:27.557895",
      "element_tag": "img",
      "title": "The French Dispatch",
      "description": "",
      "category": "Technique",
      "alt_text": "The French Dispatch",
      "css_classes": "lazy-img lazyImages1 trigger_info_",
      "file_size": null,
      "dimensions": null,
      "tags": [
        "Eyecandy",
        "lazy img",
        "trigger_info_",
        "lazyImages1"
      ]
    },
    {
      "video_url": "https://asset.eyecannndy.com/media/clip/2024/02/28/261709096816.webp",
      "page_url": "https://eyecannndy.com/technique/trucking",
      "discovered_at": "2025-09-09T08:56:27.557934",
      "element_tag": "img",
      "title": "Beethoven",
      "description": "",
      "category": "Technique",
      "alt_text": "Beethoven",
      "css_classes": "lazy-img lazyImages1 trigger_info_",
      "file_size": null,
      "dimensions": null,
      "tags": [
        "Eyecandy",
        "lazy img",
        "trigger_info_",
        "lazyImages1"
      ]
    },
    {
      "video_url": "https://asset.eyecannndy.com/media/clip/2024/01/28/261706406344.webp",
      "page_url": "https://eyecannndy.com/technique/trucking",
      "discovered_at": "2025-09-09T08:56:27.557972",
      "element_tag": "img",
      "title": "Johnnie Walker - The Next Step",
      "description": "",
      "category": "Technique",
      "alt_text": "Johnnie Walker - The Next Step",
      "css_classes": "lazy-img lazyImages1 trigger_info_",
      "file_size": null,
      "dimensions": null,
      "tags": [
        "Eyecandy",
        "lazy img",
        "trigger_info_",
        "lazyImages1"
      ]
    },
    {
      "video_url": "https://asset.eyecannndy.com/media/clip/2024/01/01/261704075163.webp",
      "page_url": "https://eyecannndy.com/technique/trucking",
      "discovered_at": "2025-09-09T08:56:27.558008",
      "element_tag": "img",
      "title": "Ford Kuga - Levels",
      "description": "",
      "category": "Technique",
      "alt_text": "Ford Kuga - Levels",
      "css_classes": "lazy-img lazyImages1 trigger_info_",
      "file_size": null,
      "dimensions": null,
      "tags": [
        "Eyecandy",
        "lazy img",
        "trigger_info_",
        "lazyImages1"
      ]
    },
    {
      "video_url": "https://asset.eyecannndy.com/media/clip/2024/02/20/261708420642.webp",
      "page_url": "https://eyecannndy.com/technique/trucking",
      "discovered_at": "2025-09-09T08:56:27.558044",
      "element_tag": "img",
      "title": "AJR - The DJ Is Crying For Help",
      "description": "",
      "category": "Technique",
      "alt_text": "AJR - The DJ Is Crying For Help",
      "css_classes": "lazy-img lazyImages1 trigger_info_",
      "file_size": null,
      "dimensions": null,
      "tags": [
        "Eyecandy",
        "lazy img",
        "trigger_info_",
        "lazyImages1"
      ]
    },
    {
      "video_url": "https://asset.eyecannndy.com/media/clip/2024/01/29/261706570119.webp",
      "page_url": "https://eyecannndy.com/technique/trucking",
      "discovered_at": "2025-09-09T08:56:27.558080",
      "element_tag": "img",
      "title": "Art by Bright Raven",
      "description": "",
      "category": "Technique",
      "alt_text": "Art by Bright Raven",
      "css_classes": "lazy-img lazyImages1 trigger_info_",
      "file_size": null,
      "dimensions": null,
      "tags": [
        "Eyecandy",
        "lazy img",
        "trigger_info_",
        "lazyImages1"
      ]
    },
    {
      "video_url": "https://asset.eyecannndy.com/media/clip/2024/03/04/261709537697.webp",
      "page_url": "https://eyecannndy.com/technique/trucking",
      "discovered_at": "2025-09-09T08:56:27.558117",
      "element_tag": "img",
      "title": "Miel De Montagne - Le Pigeon",
      "description": "",
      "category": "Technique",
      "alt_text": "Miel De Montagne - Le Pigeon",
      "css_classes": "lazy-img lazyImages1 trigger_info_",
      "file_size": null,
      "dimensions": null,
      "tags": [
        "Eyecandy",
        "lazy img",
        "trigger_info_",
        "lazyImages1"
      ]
    },
    {
      "video_url": "https://asset.eyecannndy.com/media/clip/2024/03/16/261710577948.webp",
      "page_url": "https://eyecannndy.com/technique/trucking",
      "discovered_at": "2025-09-09T08:56:27.558154",
      "element_tag": "img",
      "title": "Busta Rhymes - BIG EVERYTHING",
      "description": "",
      "category": "Technique",
      "alt_text": "Busta Rhymes - BIG EVERYTHING",
      "css_classes": "lazy-img lazyImages1 trigger_info_",
      "file_size": null,
      "dimensions": null,
      "tags": [
        "Eyecandy",
        "lazy img",
        "trigger_info_",
        "lazyImages1"
      ]
    },
    {
      "video_url": "https://asset.eyecannndy.com/media/clip/2024/01/29/261706570057.webp",
      "page_url": "https://eyecannndy.com/technique/trucking",
      "discovered_at": "2025-09-09T08:56:27.558191",
      "element_tag": "img",
      "title": "Spirited Away",
      "description": "",
      "category": "Technique",
      "alt_text": "Spirited Away",
      "css_classes": "lazy-img lazyImages1 trigger_info_",
      "file_size": null,
      "dimensions": null,
      "tags": [
        "Eyecandy",
        "lazy img",
        "trigger_info_",
        "lazyImages1"
      ]
    },
    {
      "video_url": "https://asset.eyecannndy.com/media/clip/2024/03/24/261711258123.webp",
      "page_url": "https://eyecannndy.com/technique/trucking",
      "discovered_at": "2025-09-09T08:56:27.558227",
      "element_tag": "img",
      "title": "Sam Akpro - Death By Entertainment",
      "description": "",
      "category": "Technique",
      "alt_text": "Sam Akpro - Death By Entertainment",
      "css_classes": "lazy-img lazyImages1 trigger_info_",
      "file_size": null,
      "dimensions": null,
      "tags": [
        "Eyecandy",
        "lazy img",
        "trigger_info_",
        "lazyImages1"
      ]
    },
    {
      "video_url": "https://asset.eyecannndy.com/media/clip/2024/02/20/261708420589.webp",
      "page_url": "https://eyecannndy.com/technique/trucking",
      "discovered_at": "2025-09-09T08:56:27.558267",
      "element_tag": "img",
      "title": "AJR - The DJ Is Crying For Help",
      "description": "",
      "category": "Technique",
      "alt_text": "AJR - The DJ Is Crying For Help",
      "css_classes": "lazy-img lazyImages1 trigger_info_",
      "file_size": null,
      "dimensions": null,
      "tags": [
        "Eyecandy",
        "lazy img",
        "trigger_info_",
        "lazyImages1"
      ]
    },
    {
      "video_url": "https://asset.eyecannndy.com/media/clip/2024/02/15/261707974322.webp",
      "page_url": "https://eyecannndy.com/technique/trucking",
      "discovered_at": "2025-09-09T08:56:27.558303",
      "element_tag": "img",
      "title": "Dream Corp LLC",
      "description": "",
      "category": "Technique",
      "alt_text": "Dream Corp LLC",
      "css_classes": "lazy-img lazyImages1 trigger_info_",
      "file_size": null,
      "dimensions": null,
      "tags": [
        "Eyecandy",
        "lazy img",
        "trigger_info_",
        "lazyImages1"
      ]
    },
    {
      "video_url": "https://asset.eyecannndy.com/media/clip/2023/12/30/261703899121.webp",
      "page_url": "https://eyecannndy.com/technique/trucking",
      "discovered_at": "2025-09-09T08:56:27.558339",
      "element_tag": "img",
      "title": "Childish Gambino - Sweatpants ft. Problem",
      "description": "",
      "category": "Technique",
      "alt_text": "Childish Gambino - Sweatpants ft. Problem",
      "css_classes": "lazy-img lazyImages1 trigger_info_",
      "file_size": null,
      "dimensions": null,
      "tags": [
        "Eyecandy",
        "lazy img",
        "trigger_info_",
        "lazyImages1"
      ]
    },
    {
      "video_url": "https://asset.eyecannndy.com/media/clip/2024/03/22/261711139486.webp",
      "page_url": "https://eyecannndy.com/technique/trucking",
      "discovered_at": "2025-09-09T08:56:27.558378",
      "element_tag": "img",
      "title": "Aminé - Charmander",
      "description": "",
      "category": "Technique",
      "alt_text": "Aminé - Charmander",
      "css_classes": "lazy-img lazyImages1 trigger_info_",
      "file_size": null,
      "dimensions": null,
      "tags": [
        "Eyecandy",
        "lazy img",
        "trigger_info_",
        "lazyImages1"
      ]
    },
    {
      "video_url": "https://asset.eyecannndy.com/media/clip/2024/01/28/261706406294.webp",
      "page_url": "https://eyecannndy.com/technique/trucking",
      "discovered_at": "2025-09-09T08:56:27.558414",
      "element_tag": "img",
      "title": "Johnnie Walker - The Next Step",
      "description": "",
      "category": "Technique",
      "alt_text": "Johnnie Walker - The Next Step",
      "css_classes": "lazy-img lazyImages1 trigger_info_",
      "file_size": null,
      "dimensions": null,
      "tags": [
        "Eyecandy",
        "lazy img",
        "trigger_info_",
        "lazyImages1"
      ]
    },
    {
      "video_url": "https://asset.eyecannndy.com/media/clip/2023/12/23/261703375390.webp",
      "page_url": "https://eyecannndy.com/technique/trucking",
      "discovered_at": "2025-09-09T08:56:27.558452",
      "element_tag": "img",
      "title": "The French Dispatch",
      "description": "",
      "category": "Technique",
      "alt_text": "The French Dispatch",
      "css_classes": "lazy-img lazyImages1 trigger_info_",
      "file_size": null,
      "dimensions": null,
      "tags": [
        "Eyecandy",
        "lazy img",
        "trigger_info_",
        "lazyImages1"
      ]
    },
    {
      "video_url": "https://asset.eyecannndy.com/media/clip/2024/01/29/261706572055.webp",
      "page_url": "https://eyecannndy.com/technique/trucking",
      "discovered_at": "2025-09-09T08:56:27.558488",
      "element_tag": "img",
      "title": "Lazy Susan",
      "description": "",
      "category": "Technique",
      "alt_text": "Lazy Susan",
      "css_classes": "lazy-img lazyImages1 trigger_info_",
      "file_size": null,
      "dimensions": null,
      "tags": [
        "Eyecandy",
        "lazy img",
        "trigger_info_",
        "lazyImages1"
      ]
    },
    {
      "video_url": "https://asset.eyecannndy.com/media/clip/2024/01/28/261706406255.webp",
      "page_url": "https://eyecannndy.com/technique/trucking",
      "discovered_at": "2025-09-09T08:56:27.558532",
      "element_tag": "img",
      "title": "Johnnie Walker - The Next Step",
      "description": "",
      "category": "Technique",
      "alt_text": "Johnnie Walker - The Next Step",
      "css_classes": "lazy-img lazyImages1 trigger_info_",
      "file_size": null,
      "dimensions": null,
      "tags": [
        "Eyecandy",
        "lazy img",
        "trigger_info_",
        "lazyImages1"
      ]
    },
    {
      "video_url": "https://asset.eyecannndy.com/media/clip/2024/01/13/261705177320.webp",
      "page_url": "https://eyecannndy.com/technique/trucking",
      "discovered_at": "2025-09-09T08:56:27.558568",
      "element_tag": "img",
      "title": "Adidas - Feel the Boost",
      "description": "",
      "category": "Technique",
      "alt_text": "Adidas - Feel the Boost",
      "css_classes": "lazy-img lazyImages1 trigger_info_",
      "file_size": null,
      "dimensions": null,
      "tags": [
        "Eyecandy",
        "lazy img",
        "trigger_info_",
        "lazyImages1"
      ]
    },
    {
      "video_url": "https://asset.eyecannndy.com/media/clip/2024/01/29/261706571208.webp",
      "page_url": "https://eyecannndy.com/technique/trucking",
      "discovered_at": "2025-09-09T08:56:27.558607",
      "element_tag": "img",
      "title": "Absolut - The Walk",
      "description": "",
      "category": "Technique",
      "alt_text": "Absolut - The Walk",
      "css_classes": "lazy-img lazyImages1 trigger_info_",
      "file_size": null,
      "dimensions": null,
      "tags": [
        "Eyecandy",
        "lazy img",
        "trigger_info_",
        "lazyImages1"
      ]
    },
    {
      "video_url": "https://asset.eyecannndy.com/media/clip/2024/01/29/261706570488.webp",
      "page_url": "https://eyecannndy.com/technique/trucking",
      "discovered_at": "2025-09-09T08:56:27.558699",
      "element_tag": "img",
      "title": "The Shining",
      "description": "",
      "category": "Technique",
      "alt_text": "The Shining",
      "css_classes": "lazy-img lazyImages1 trigger_info_",
      "file_size": null,
      "dimensions": null,
      "tags": [
        "Eyecandy",
        "lazy img",
        "trigger_info_",
        "lazyImages1"
      ]
    },
    {
      "video_url": "https://asset.eyecannndy.com/media/clip/2024/01/28/261706400370.webp",
      "page_url": "https://eyecannndy.com/technique/trucking",
      "discovered_at": "2025-09-09T08:56:27.558772",
      "element_tag": "img",
      "title": "Bourne - Ere We Go",
      "description": "",
      "category": "Technique",
      "alt_text": "Bourne - Ere We Go",
      "css_classes": "lazy-img lazyImages1 trigger_info_",
      "file_size": null,
      "dimensions": null,
      "tags": [
        "Eyecandy",
        "lazy img",
        "trigger_info_",
        "lazyImages1"
      ]
    },
    {
      "video_url": "https://asset.eyecannndy.com/media/clip/2024/05/15/261715812366.webp",
      "page_url": "https://eyecannndy.com/technique/trucking",
      "discovered_at": "2025-09-09T08:56:27.558821",
      "element_tag": "img",
      "title": "Sabrina Carpenter - Espresso",
      "description": "",
      "category": "Technique",
      "alt_text": "Sabrina Carpenter - Espresso",
      "css_classes": "lazy-img lazyImages1 trigger_info_",
      "file_size": null,
      "dimensions": null,
      "tags": [
        "Eyecandy",
        "lazy img",
        "trigger_info_",
        "lazyImages1"
      ]
    },
    {
      "video_url": "https://asset.eyecannndy.com/media/clip/2025/02/10/261739169724.webp",
      "page_url": "https://eyecannndy.com/technique/trucking",
      "discovered_at": "2025-09-09T08:56:27.558867",
      "element_tag": "img",
      "title": "GIVĒON - TWENTIES",
      "description": "",
      "category": "Technique",
      "alt_text": "GIVĒON - TWENTIES",
      "css_classes": "lazy-img lazyImages1 trigger_info_",
      "file_size": null,
      "dimensions": null,
      "tags": [
        "Eyecandy",
        "lazy img",
        "trigger_info_",
        "lazyImages1"
      ]
    },
    {
      "video_url": "https://asset.eyecannndy.com/media/clip/2024/03/26/261711436246.webp",
      "page_url": "https://eyecannndy.com/technique/trucking",
      "discovered_at": "2025-09-09T08:56:27.558908",
      "element_tag": "img",
      "title": "Killdummies - Keine War Großartig//Fukk U",
      "description": "",
      "category": "Technique",
      "alt_text": "Killdummies - Keine War Großartig//Fukk U",
      "css_classes": "lazy-img lazyImages1 trigger_info_",
      "file_size": null,
      "dimensions": null,
      "tags": [
        "Eyecandy",
        "lazy img",
        "trigger_info_",
        "lazyImages1"
      ]
    },
    {
      "video_url": "https://asset.eyecannndy.com/media/clip/2024/01/04/261704385597.webp",
      "page_url": "https://eyecannndy.com/technique/trucking",
      "discovered_at": "2025-09-09T08:56:27.558949",
      "element_tag": "img",
      "title": "Asteroid City",
      "description": "",
      "category": "Technique",
      "alt_text": "Asteroid City",
      "css_classes": "lazy-img lazyImages1 trigger_info_",
      "file_size": null,
      "dimensions": null,
      "tags": [
        "Eyecandy",
        "lazy img",
        "trigger_info_",
        "lazyImages1"
      ]
    },
    {
      "video_url": "https://asset.eyecannndy.com/media/clip/2024/03/31/261711860570.webp",
      "page_url": "https://eyecannndy.com/technique/trucking",
      "discovered_at": "2025-09-09T08:56:27.558990",
      "element_tag": "img",
      "title": "Nike - A Feel For Every You",
      "description": "",
      "category": "Technique",
      "alt_text": "Nike - A Feel For Every You",
      "css_classes": "lazy-img lazyImages1 trigger_info_",
      "file_size": null,
      "dimensions": null,
      "tags": [
        "Eyecandy",
        "lazy img",
        "trigger_info_",
        "lazyImages1"
      ]
    },
    {
      "video_url": "https://asset.eyecannndy.com/media/clip/2024/01/29/261706572377.webp",
      "page_url": "https://eyecannndy.com/technique/trucking",
      "discovered_at": "2025-09-09T08:56:27.559029",
      "element_tag": "img",
      "title": "1917",
      "description": "",
      "category": "Technique",
      "alt_text": "1917",
      "css_classes": "lazy-img lazyImages1 trigger_info_",
      "file_size": null,
      "dimensions": null,
      "tags": [
        "Eyecandy",
        "lazy img",
        "trigger_info_",
        "lazyImages1"
      ]
    },
    {
      "video_url": "https://asset.eyecannndy.com/media/clip/2024/01/25/261706174497.webp",
      "page_url": "https://eyecannndy.com/technique/trucking",
      "discovered_at": "2025-09-09T08:56:27.559067",
      "element_tag": "img",
      "title": "Snowpiercer",
      "description": "",
      "category": "Technique",
      "alt_text": "Snowpiercer",
      "css_classes": "lazy-img lazyImages1 trigger_info_",
      "file_size": null,
      "dimensions": null,
      "tags": [
        "Eyecandy",
        "lazy img",
        "trigger_info_",
        "lazyImages1"
      ]
    },
    {
      "video_url": "https://asset.eyecannndy.com/media/clip/2024/03/19/261710831657.webp",
      "page_url": "https://eyecannndy.com/technique/trucking",
      "discovered_at": "2025-09-09T08:56:27.559104",
      "element_tag": "img",
      "title": "Oppo - Make Every Shot Stand Out",
      "description": "",
      "category": "Technique",
      "alt_text": "Oppo - Make Every Shot Stand Out",
      "css_classes": "lazy-img lazyImages1 trigger_info_",
      "file_size": null,
      "dimensions": null,
      "tags": [
        "Eyecandy",
        "lazy img",
        "trigger_info_",
        "lazyImages1"
      ]
    },
    {
      "video_url": "https://asset.eyecannndy.com/media/clip/2024/03/09/261710026608.webp",
      "page_url": "https://eyecannndy.com/technique/trucking",
      "discovered_at": "2025-09-09T08:56:27.559144",
      "element_tag": "img",
      "title": "The Gentlemen (TV Series)",
      "description": "",
      "category": "Technique",
      "alt_text": "The Gentlemen (TV Series)",
      "css_classes": "lazy-img lazyImages1 trigger_info_",
      "file_size": null,
      "dimensions": null,
      "tags": [
        "Eyecandy",
        "lazy img",
        "trigger_info_",
        "lazyImages1"
      ]
    },
    {
      "video_url": "https://asset.eyecannndy.com/media/clip/2024/09/12/261726175209.webp",
      "page_url": "https://eyecannndy.com/technique/trucking",
      "discovered_at": "2025-09-09T08:56:27.559181",
      "element_tag": "img",
      "title": "M.I.A. 'Bad Girls'",
      "description": "",
      "category": "Technique",
      "alt_text": "M.I.A. 'Bad Girls'",
      "css_classes": "lazy-img lazyImages1 trigger_info_",
      "file_size": null,
      "dimensions": null,
      "tags": [
        "Eyecandy",
        "lazy img",
        "trigger_info_",
        "lazyImages1"
      ]
    },
    {
      "video_url": "https://asset.eyecannndy.com/media/clip/2024/02/28/261709105786.webp",
      "page_url": "https://eyecannndy.com/technique/trucking",
      "discovered_at": "2025-09-09T08:56:27.559218",
      "element_tag": "img",
      "title": "Watchtower of Turkey",
      "description": "",
      "category": "Technique",
      "alt_text": "Watchtower of Turkey",
      "css_classes": "lazy-img lazyImages1 trigger_info_",
      "file_size": null,
      "dimensions": null,
      "tags": [
        "Eyecandy",
        "lazy img",
        "trigger_info_",
        "lazyImages1"
      ]
    },
    {
      "video_url": "https://asset.eyecannndy.com/media/clip/2024/02/19/261708335213.webp",
      "page_url": "https://eyecannndy.com/technique/trucking",
      "discovered_at": "2025-09-09T08:56:27.559257",
      "element_tag": "img",
      "title": "AJR - Maybe Man",
      "description": "",
      "category": "Technique",
      "alt_text": "AJR - Maybe Man",
      "css_classes": "lazy-img lazyImages1 trigger_info_",
      "file_size": null,
      "dimensions": null,
      "tags": [
        "Eyecandy",
        "lazy img",
        "trigger_info_",
        "lazyImages1"
      ]
    },
    {
      "video_url": "https://asset.eyecannndy.com/media/clip/2024/01/29/261706565616.webp",
      "page_url": "https://eyecannndy.com/technique/trucking",
      "discovered_at": "2025-09-09T08:56:27.559293",
      "element_tag": "img",
      "title": "The French Dispatch",
      "description": "",
      "category": "Technique",
      "alt_text": "The French Dispatch",
      "css_classes": "lazy-img lazyImages1 trigger_info_",
      "file_size": null,
      "dimensions": null,
      "tags": [
        "Eyecandy",
        "lazy img",
        "trigger_info_",
        "lazyImages1"
      ]
    },
    {
      "video_url": "https://asset.eyecannndy.com/media/clip/2024/01/26/261706259467.webp",
      "page_url": "https://eyecannndy.com/technique/trucking",
      "discovered_at": "2025-09-09T08:56:27.559330",
      "element_tag": "img",
      "title": "Art by Paul Trillo",
      "description": "",
      "category": "Technique",
      "alt_text": "Art by Paul Trillo",
      "css_classes": "lazy-img lazyImages1 trigger_info_",
      "file_size": null,
      "dimensions": null,
      "tags": [
        "Eyecandy",
        "lazy img",
        "trigger_info_",
        "lazyImages1"
      ]
    },
    {
      "video_url": "https://asset.eyecannndy.com/media/clip/2024/03/19/261710831840.webp",
      "page_url": "https://eyecannndy.com/technique/trucking",
      "discovered_at": "2025-09-09T08:56:27.559367",
      "element_tag": "img",
      "title": "Oppo - Make Every Shot Stand Out",
      "description": "",
      "category": "Technique",
      "alt_text": "Oppo - Make Every Shot Stand Out",
      "css_classes": "lazy-img lazyImages1 trigger_info_",
      "file_size": null,
      "dimensions": null,
      "tags": [
        "Eyecandy",
        "lazy img",
        "trigger_info_",
        "lazyImages1"
      ]
    },
    {
      "video_url": "https://asset.eyecannndy.com/media/clip/2024/02/11/261707642245.webp",
      "page_url": "https://eyecannndy.com/technique/trucking",
      "discovered_at": "2025-09-09T08:56:27.559403",
      "element_tag": "img",
      "title": "Nu Genea - Marechià (with Célia Kameni)",
      "description": "",
      "category": "Technique",
      "alt_text": "Nu Genea - Marechià (with Célia Kameni)",
      "css_classes": "lazy-img lazyImages1 trigger_info_",
      "file_size": null,
      "dimensions": null,
      "tags": [
        "Eyecandy",
        "lazy img",
        "trigger_info_",
        "lazyImages1"
      ]
    },
    {
      "video_url": "https://asset.eyecannndy.com/media/clip/2024/03/06/261709716284.webp",
      "page_url": "https://eyecannndy.com/technique/trucking",
      "discovered_at": "2025-09-09T08:56:27.559441",
      "element_tag": "img",
      "title": "Poor Things",
      "description": "",
      "category": "Technique",
      "alt_text": "Poor Things",
      "css_classes": "lazy-img lazyImages1 trigger_info_",
      "file_size": null,
      "dimensions": null,
      "tags": [
        "Eyecandy",
        "lazy img",
        "trigger_info_",
        "lazyImages1"
      ]
    },
    {
      "video_url": "https://asset.eyecannndy.com/media/clip/2024/03/13/261710332560.webp",
      "page_url": "https://eyecannndy.com/technique/trucking",
      "discovered_at": "2025-09-09T08:56:27.559478",
      "element_tag": "img",
      "title": "Our England",
      "description": "",
      "category": "Technique",
      "alt_text": "Our England",
      "css_classes": "lazy-img lazyImages1 trigger_info_",
      "file_size": null,
      "dimensions": null,
      "tags": [
        "Eyecandy",
        "lazy img",
        "trigger_info_",
        "lazyImages1"
      ]
    },
    {
      "video_url": "https://asset.eyecannndy.com/media/clip/2024/01/28/261706426793.webp",
      "page_url": "https://eyecannndy.com/technique/trucking",
      "discovered_at": "2025-09-09T08:56:27.559516",
      "element_tag": "img",
      "title": "The Lighthouse",
      "description": "",
      "category": "Technique",
      "alt_text": "The Lighthouse",
      "css_classes": "lazy-img lazyImages1 trigger_info_",
      "file_size": null,
      "dimensions": null,
      "tags": [
        "Eyecandy",
        "lazy img",
        "trigger_info_",
        "lazyImages1"
      ]
    },
    {
      "video_url": "https://asset.eyecannndy.com/media/clip/2024/03/22/261711139547.webp",
      "page_url": "https://eyecannndy.com/technique/trucking",
      "discovered_at": "2025-09-09T08:56:27.559554",
      "element_tag": "img",
      "title": "Aminé - Charmander",
      "description": "",
      "category": "Technique",
      "alt_text": "Aminé - Charmander",
      "css_classes": "lazy-img lazyImages1 trigger_info_",
      "file_size": null,
      "dimensions": null,
      "tags": [
        "Eyecandy",
        "lazy img",
        "trigger_info_",
        "lazyImages1"
      ]
    },
    {
      "video_url": "https://asset.eyecannndy.com/media/clip/2025/02/10/261739169441.webp",
      "page_url": "https://eyecannndy.com/technique/trucking",
      "discovered_at": "2025-09-09T08:56:27.559592",
      "element_tag": "img",
      "title": "GIVĒON - TWENTIES",
      "description": "",
      "category": "Technique",
      "alt_text": "GIVĒON - TWENTIES",
      "css_classes": "lazy-img lazyImages1 trigger_info_",
      "file_size": null,
      "dimensions": null,
      "tags": [
        "Eyecandy",
        "lazy img",
        "trigger_info_",
        "lazyImages1"
      ]
    },
    {
      "video_url": "https://asset.eyecannndy.com/media/clip/2023/12/24/261703400196.webp",
      "page_url": "https://eyecannndy.com/technique/trucking",
      "discovered_at": "2025-09-09T08:56:27.559628",
      "element_tag": "img",
      "title": "adidas Originals - Original Is Never Finished",
      "description": "",
      "category": "Technique",
      "alt_text": "adidas Originals - Original Is Never Finished",
      "css_classes": "lazy-img lazyImages1 trigger_info_",
      "file_size": null,
      "dimensions": null,
      "tags": [
        "Eyecandy",
        "lazy img",
        "trigger_info_",
        "lazyImages1"
      ]
    },
    {
      "video_url": "https://asset.eyecannndy.com/media/clip/2024/01/13/261705173413.webp",
      "page_url": "https://eyecannndy.com/technique/trucking",
      "discovered_at": "2025-09-09T08:56:27.559673",
      "element_tag": "img",
      "title": "Apple - Hello Yellow",
      "description": "",
      "category": "Technique",
      "alt_text": "Apple - Hello Yellow",
      "css_classes": "lazy-img lazyImages1 trigger_info_",
      "file_size": null,
      "dimensions": null,
      "tags": [
        "Eyecandy",
        "lazy img",
        "trigger_info_",
        "lazyImages1"
      ]
    },
    {
      "video_url": "https://asset.eyecannndy.com/media/clip/2024/03/04/261709538820.webp",
      "page_url": "https://eyecannndy.com/technique/trucking",
      "discovered_at": "2025-09-09T08:56:27.559713",
      "element_tag": "img",
      "title": "Saint Levant - Nails",
      "description": "",
      "category": "Technique",
      "alt_text": "Saint Levant - Nails",
      "css_classes": "lazy-img lazyImages1 trigger_info_",
      "file_size": null,
      "dimensions": null,
      "tags": [
        "Eyecandy",
        "lazy img",
        "trigger_info_",
        "lazyImages1"
      ]
    },
    {
      "video_url": "https://asset.eyecannndy.com/media/clip/2023/12/30/261703898814.webp",
      "page_url": "https://eyecannndy.com/technique/trucking",
      "discovered_at": "2025-09-09T08:56:27.559749",
      "element_tag": "img",
      "title": "Childish Gambino - Sweatpants ft. Problem",
      "description": "",
      "category": "Technique",
      "alt_text": "Childish Gambino - Sweatpants ft. Problem",
      "css_classes": "lazy-img lazyImages1 trigger_info_",
      "file_size": null,
      "dimensions": null,
      "tags": [
        "Eyecandy",
        "lazy img",
        "trigger_info_",
        "lazyImages1"
      ]
    },
    {
      "video_url": "https://asset.eyecannndy.com/media/clip/2024/01/28/261706406080.webp",
      "page_url": "https://eyecannndy.com/technique/trucking",
      "discovered_at": "2025-09-09T08:56:27.559786",
      "element_tag": "img",
      "title": "Johnnie Walker - The Next Step",
      "description": "",
      "category": "Technique",
      "alt_text": "Johnnie Walker - The Next Step",
      "css_classes": "lazy-img lazyImages1 trigger_info_",
      "file_size": null,
      "dimensions": null,
      "tags": [
        "Eyecandy",
        "lazy img",
        "trigger_info_",
        "lazyImages1"
      ]
    },
    {
      "video_url": "https://asset.eyecannndy.com/media/clip/2024/01/29/261706572323.webp",
      "page_url": "https://eyecannndy.com/technique/trucking",
      "discovered_at": "2025-09-09T08:56:27.559822",
      "element_tag": "img",
      "title": "1917",
      "description": "",
      "category": "Technique",
      "alt_text": "1917",
      "css_classes": "lazy-img lazyImages1 trigger_info_",
      "file_size": null,
      "dimensions": null,
      "tags": [
        "Eyecandy",
        "lazy img",
        "trigger_info_",
        "lazyImages1"
      ]
    },
    {
      "video_url": "https://asset.eyecannndy.com/media/clip/2024/03/25/261711343806.webp",
      "page_url": "https://eyecannndy.com/technique/trucking",
      "discovered_at": "2025-09-09T08:56:27.559857",
      "element_tag": "img",
      "title": "Fantastic Mr. Fox",
      "description": "",
      "category": "Technique",
      "alt_text": "Fantastic Mr. Fox",
      "css_classes": "lazy-img lazyImages1 trigger_info_",
      "file_size": null,
      "dimensions": null,
      "tags": [
        "Eyecandy",
        "lazy img",
        "trigger_info_",
        "lazyImages1"
      ]
    },
    {
      "video_url": "https://asset.eyecannndy.com/media/clip/2024/03/25/261711341565.webp",
      "page_url": "https://eyecannndy.com/technique/trucking",
      "discovered_at": "2025-09-09T08:56:27.559893",
      "element_tag": "img",
      "title": "Fantastic Mr. Fox",
      "description": "",
      "category": "Technique",
      "alt_text": "Fantastic Mr. Fox",
      "css_classes": "lazy-img lazyImages1 trigger_info_",
      "file_size": null,
      "dimensions": null,
      "tags": [
        "Eyecandy",
        "lazy img",
        "trigger_info_",
        "lazyImages1"
      ]
    },
    {
      "video_url": "https://asset.eyecannndy.com/media/clip/2024/09/12/261726174206.webp",
      "page_url": "https://eyecannndy.com/technique/trucking",
      "discovered_at": "2025-09-09T08:56:27.559929",
      "element_tag": "img",
      "title": "M.I.A. 'Bad Girls'",
      "description": "",
      "category": "Technique",
      "alt_text": "M.I.A. 'Bad Girls'",
      "css_classes": "lazy-img lazyImages1 trigger_info_",
      "file_size": null,
      "dimensions": null,
      "tags": [
        "Eyecandy",
        "lazy img",
        "trigger_info_",
        "lazyImages1"
      ]
    },
    {
      "video_url": "https://asset.eyecannndy.com/media/clip/2024/03/31/261711860931.webp",
      "page_url": "https://eyecannndy.com/technique/trucking",
      "discovered_at": "2025-09-09T08:56:27.559965",
      "element_tag": "img",
      "title": "Nike - A Feel For Every You",
      "description": "",
      "category": "Technique",
      "alt_text": "Nike - A Feel For Every You",
      "css_classes": "lazy-img lazyImages1 trigger_info_",
      "file_size": null,
      "dimensions": null,
      "tags": [
        "Eyecandy",
        "lazy img",
        "trigger_info_",
        "lazyImages1"
      ]
    },
    {
      "video_url": "https://asset.eyecannndy.com/media/clip/2024/03/25/261711343049.webp",
      "page_url": "https://eyecannndy.com/technique/trucking",
      "discovered_at": "2025-09-09T08:56:27.560001",
      "element_tag": "img",
      "title": "Fantastic Mr. Fox",
      "description": "",
      "category": "Technique",
      "alt_text": "Fantastic Mr. Fox",
      "css_classes": "lazy-img lazyImages1 trigger_info_",
      "file_size": null,
      "dimensions": null,
      "tags": [
        "Eyecandy",
        "lazy img",
        "trigger_info_",
        "lazyImages1"
      ]
    },
    {
      "video_url": "https://asset.eyecannndy.com/media/clip/2024/01/13/261705115998.webp",
      "page_url": "https://eyecannndy.com/technique/trucking",
      "discovered_at": "2025-09-09T08:56:27.560038",
      "element_tag": "img",
      "title": "Adidas - Hello Tomorrow",
      "description": "",
      "category": "Technique",
      "alt_text": "Adidas - Hello Tomorrow",
      "css_classes": "lazy-img lazyImages1 trigger_info_",
      "file_size": null,
      "dimensions": null,
      "tags": [
        "Eyecandy",
        "lazy img",
        "trigger_info_",
        "lazyImages1"
      ]
    },
    {
      "video_url": "https://asset.eyecannndy.com/media/clip/2024/02/14/261707902114.webp",
      "page_url": "https://eyecannndy.com/technique/trucking",
      "discovered_at": "2025-09-09T08:56:27.560074",
      "element_tag": "img",
      "title": "Zodiac",
      "description": "",
      "category": "Technique",
      "alt_text": "Zodiac",
      "css_classes": "lazy-img lazyImages1 trigger_info_",
      "file_size": null,
      "dimensions": null,
      "tags": [
        "Eyecandy",
        "lazy img",
        "trigger_info_",
        "lazyImages1"
      ]
    },
    {
      "video_url": "https://asset.eyecannndy.com/media/clip/2023/12/20/261703043655.webp",
      "page_url": "https://eyecannndy.com/technique/trucking",
      "discovered_at": "2025-09-09T08:56:27.560111",
      "element_tag": "img",
      "title": "Asteroid City",
      "description": "",
      "category": "Technique",
      "alt_text": "Asteroid City",
      "css_classes": "lazy-img lazyImages1 trigger_info_",
      "file_size": null,
      "dimensions": null,
      "tags": [
        "Eyecandy",
        "lazy img",
        "trigger_info_",
        "lazyImages1"
      ]
    },
    {
      "video_url": "https://asset.eyecannndy.com/media/clip/2024/01/29/261706570164.webp",
      "page_url": "https://eyecannndy.com/technique/trucking",
      "discovered_at": "2025-09-09T08:56:27.560147",
      "element_tag": "img",
      "title": "The French Dispatch",
      "description": "",
      "category": "Technique",
      "alt_text": "The French Dispatch",
      "css_classes": "lazy-img lazyImages1 trigger_info_",
      "file_size": null,
      "dimensions": null,
      "tags": [
        "Eyecandy",
        "lazy img",
        "trigger_info_",
        "lazyImages1"
      ]
    },
    {
      "video_url": "https://asset.eyecannndy.com/media/clip/2024/01/23/261705997764.webp",
      "page_url": "https://eyecannndy.com/technique/trucking",
      "discovered_at": "2025-09-09T08:56:27.560183",
      "element_tag": "img",
      "title": "Lil Dicky - HAHAHA",
      "description": "",
      "category": "Technique",
      "alt_text": "Lil Dicky - HAHAHA",
      "css_classes": "lazy-img lazyImages1 trigger_info_",
      "file_size": null,
      "dimensions": null,
      "tags": [
        "Eyecandy",
        "lazy img",
        "trigger_info_",
        "lazyImages1"
      ]
    },
    {
      "video_url": "https://asset.eyecannndy.com/media/clip/2024/02/19/261708336464.webp",
      "page_url": "https://eyecannndy.com/technique/trucking",
      "discovered_at": "2025-09-09T08:56:27.560219",
      "element_tag": "img",
      "title": "AJR - Maybe Man",
      "description": "",
      "category": "Technique",
      "alt_text": "AJR - Maybe Man",
      "css_classes": "lazy-img lazyImages1 trigger_info_",
      "file_size": null,
      "dimensions": null,
      "tags": [
        "Eyecandy",
        "lazy img",
        "trigger_info_",
        "lazyImages1"
      ]
    },
    {
      "video_url": "https://asset.eyecannndy.com/media/clip/2024/05/09/261715294754.webp",
      "page_url": "https://eyecannndy.com/technique/trucking",
      "discovered_at": "2025-09-09T08:56:27.560254",
      "element_tag": "img",
      "title": "Shit Robot \"Take 'Em Up\"",
      "description": "",
      "category": "Technique",
      "alt_text": "Shit Robot \"Take 'Em Up\"",
      "css_classes": "lazy-img lazyImages1 trigger_info_",
      "file_size": null,
      "dimensions": null,
      "tags": [
        "Eyecandy",
        "lazy img",
        "trigger_info_",
        "lazyImages1"
      ]
    },
    {
      "video_url": "https://asset.eyecannndy.com/media/clip/2024/03/02/261709339628.webp",
      "page_url": "https://eyecannndy.com/technique/trucking",
      "discovered_at": "2025-09-09T08:56:27.560289",
      "element_tag": "img",
      "title": "Brooks - Gravity Had a Good Run",
      "description": "",
      "category": "Technique",
      "alt_text": "Brooks - Gravity Had a Good Run",
      "css_classes": "lazy-img lazyImages1 trigger_info_",
      "file_size": null,
      "dimensions": null,
      "tags": [
        "Eyecandy",
        "lazy img",
        "trigger_info_",
        "lazyImages1"
      ]
    },
    {
      "video_url": "https://asset.eyecannndy.com/media/clip/2024/03/24/261711251411.webp",
      "page_url": "https://eyecannndy.com/technique/trucking",
      "discovered_at": "2025-09-09T08:56:27.560325",
      "element_tag": "img",
      "title": "KYLE - iSpy feat. Lil Yachty",
      "description": "",
      "category": "Technique",
      "alt_text": "KYLE - iSpy feat. Lil Yachty",
      "css_classes": "lazy-img lazyImages1 trigger_info_",
      "file_size": null,
      "dimensions": null,
      "tags": [
        "Eyecandy",
        "lazy img",
        "trigger_info_",
        "lazyImages1"
      ]
    },
    {
      "video_url": "https://asset.eyecannndy.com/media/clip/2024/09/12/261726174420.webp",
      "page_url": "https://eyecannndy.com/technique/trucking",
      "discovered_at": "2025-09-09T08:56:27.560361",
      "element_tag": "img",
      "title": "M.I.A. 'Bad Girls'",
      "description": "",
      "category": "Technique",
      "alt_text": "M.I.A. 'Bad Girls'",
      "css_classes": "lazy-img lazyImages1 trigger_info_",
      "file_size": null,
      "dimensions": null,
      "tags": [
        "Eyecandy",
        "lazy img",
        "trigger_info_",
        "lazyImages1"
      ]
    },
    {
      "video_url": "https://asset.eyecannndy.com/media/clip/2025/02/10/261739169034.webp",
      "page_url": "https://eyecannndy.com/technique/trucking",
      "discovered_at": "2025-09-09T08:56:27.560398",
      "element_tag": "img",
      "title": "GIVĒON - TWENTIES",
      "description": "",
      "category": "Technique",
      "alt_text": "GIVĒON - TWENTIES",
      "css_classes": "lazy-img lazyImages1 trigger_info_",
      "file_size": null,
      "dimensions": null,
      "tags": [
        "Eyecandy",
        "lazy img",
        "trigger_info_",
        "lazyImages1"
      ]
    },
    {
      "video_url": "https://asset.eyecannndy.com/media/clip/2023/12/20/261703056172.webp",
      "page_url": "https://eyecannndy.com/technique/trucking",
      "discovered_at": "2025-09-09T08:56:27.560435",
      "element_tag": "img",
      "title": "Barbie",
      "description": "",
      "category": "Technique",
      "alt_text": "Barbie",
      "css_classes": "lazy-img lazyImages1 trigger_info_",
      "file_size": null,
      "dimensions": null,
      "tags": [
        "Eyecandy",
        "lazy img",
        "trigger_info_",
        "lazyImages1"
      ]
    },
    {
      "video_url": "https://asset.eyecannndy.com/media/clip/2024/01/30/261706573152.webp",
      "page_url": "https://eyecannndy.com/technique/trucking",
      "discovered_at": "2025-09-09T08:56:27.560472",
      "element_tag": "img",
      "title": "Unknown source",
      "description": "",
      "category": "Technique",
      "alt_text": "Unknown source",
      "css_classes": "lazy-img lazyImages1 trigger_info_",
      "file_size": null,
      "dimensions": null,
      "tags": [
        "Eyecandy",
        "lazy img",
        "trigger_info_",
        "lazyImages1"
      ]
    },
    {
      "video_url": "https://asset.eyecannndy.com/media/clip/2024/01/29/261706570300.webp",
      "page_url": "https://eyecannndy.com/technique/trucking",
      "discovered_at": "2025-09-09T08:56:27.560508",
      "element_tag": "img",
      "title": "Atonement",
      "description": "",
      "category": "Technique",
      "alt_text": "Atonement",
      "css_classes": "lazy-img lazyImages1 trigger_info_",
      "file_size": null,
      "dimensions": null,
      "tags": [
        "Eyecandy",
        "lazy img",
        "trigger_info_",
        "lazyImages1"
      ]
    },
    {
      "video_url": "https://asset.eyecannndy.com/media/clip/2023/12/24/261703400907.webp",
      "page_url": "https://eyecannndy.com/technique/trucking",
      "discovered_at": "2025-09-09T08:56:27.560544",
      "element_tag": "img",
      "title": "adidas Originals - Original Is Never Finished",
      "description": "",
      "category": "Technique",
      "alt_text": "adidas Originals - Original Is Never Finished",
      "css_classes": "lazy-img lazyImages1 trigger_info_",
      "file_size": null,
      "dimensions": null,
      "tags": [
        "Eyecandy",
        "lazy img",
        "trigger_info_",
        "lazyImages1"
      ]
    },
    {
      "video_url": "https://asset.eyecannndy.com/media/clip/2024/01/07/261704609229.webp",
      "page_url": "https://eyecannndy.com/technique/trucking",
      "discovered_at": "2025-09-09T08:56:27.560586",
      "element_tag": "img",
      "title": "Carly Gibert - Dropping Seeds",
      "description": "",
      "category": "Technique",
      "alt_text": "Carly Gibert - Dropping Seeds",
      "css_classes": "lazy-img lazyImages1 trigger_info_",
      "file_size": null,
      "dimensions": null,
      "tags": [
        "Eyecandy",
        "lazy img",
        "trigger_info_",
        "lazyImages1"
      ]
    },
    {
      "video_url": "https://asset.eyecannndy.com/media/clip/2024/01/01/261704075431.webp",
      "page_url": "https://eyecannndy.com/technique/trucking",
      "discovered_at": "2025-09-09T08:56:27.560623",
      "element_tag": "img",
      "title": "Ford Kuga - Levels",
      "description": "",
      "category": "Technique",
      "alt_text": "Ford Kuga - Levels",
      "css_classes": "lazy-img lazyImages1 trigger_info_",
      "file_size": null,
      "dimensions": null,
      "tags": [
        "Eyecandy",
        "lazy img",
        "trigger_info_",
        "lazyImages1"
      ]
    },
    {
      "video_url": "https://asset.eyecannndy.com/media/clip/2024/01/15/261705287862.webp",
      "page_url": "https://eyecannndy.com/technique/trucking",
      "discovered_at": "2025-09-09T08:56:27.560733",
      "element_tag": "img",
      "title": "Squarespace - The Singularity",
      "description": "",
      "category": "Technique",
      "alt_text": "Squarespace - The Singularity",
      "css_classes": "lazy-img lazyImages1 trigger_info_",
      "file_size": null,
      "dimensions": null,
      "tags": [
        "Eyecandy",
        "lazy img",
        "trigger_info_",
        "lazyImages1"
      ]
    },
    {
      "video_url": "https://asset.eyecannndy.com/media/clip/2024/01/04/261704384449.webp",
      "page_url": "https://eyecannndy.com/technique/trucking",
      "discovered_at": "2025-09-09T08:56:27.560778",
      "element_tag": "img",
      "title": "Asteroid City",
      "description": "",
      "category": "Technique",
      "alt_text": "Asteroid City",
      "css_classes": "lazy-img lazyImages1 trigger_info_",
      "file_size": null,
      "dimensions": null,
      "tags": [
        "Eyecandy",
        "lazy img",
        "trigger_info_",
        "lazyImages1"
      ]
    },
    {
      "video_url": "https://asset.eyecannndy.com/media/clip/2024/01/28/261706406134.webp",
      "page_url": "https://eyecannndy.com/technique/trucking",
      "discovered_at": "2025-09-09T08:56:27.560818",
      "element_tag": "img",
      "title": "Johnnie Walker - The Next Step",
      "description": "",
      "category": "Technique",
      "alt_text": "Johnnie Walker - The Next Step",
      "css_classes": "lazy-img lazyImages1 trigger_info_",
      "file_size": null,
      "dimensions": null,
      "tags": [
        "Eyecandy",
        "lazy img",
        "trigger_info_",
        "lazyImages1"
      ]
    },
    {
      "video_url": "https://asset.eyecannndy.com/media/clip/2025/02/10/261739171628.webp",
      "page_url": "https://eyecannndy.com/technique/trucking",
      "discovered_at": "2025-09-09T08:56:27.560859",
      "element_tag": "img",
      "title": "Doechii - DENIAL IS A RIVER",
      "description": "",
      "category": "Technique",
      "alt_text": "Doechii - DENIAL IS A RIVER",
      "css_classes": "lazy-img lazyImages1 trigger_info_",
      "file_size": null,
      "dimensions": null,
      "tags": [
        "Eyecandy",
        "lazy img",
        "trigger_info_",
        "lazyImages1"
      ]
    },
    {
      "video_url": "https://asset.eyecannndy.com/media/clip/2023/12/20/261703042431.webp",
      "page_url": "https://eyecannndy.com/technique/trucking",
      "discovered_at": "2025-09-09T08:56:27.560898",
      "element_tag": "img",
      "title": "Nomadland",
      "description": "",
      "category": "Technique",
      "alt_text": "Nomadland",
      "css_classes": "lazy-img lazyImages1 trigger_info_",
      "file_size": null,
      "dimensions": null,
      "tags": [
        "Eyecandy",
        "lazy img",
        "trigger_info_",
        "lazyImages1"
      ]
    },
    {
      "video_url": "https://asset.eyecannndy.com/media/clip/2024/01/29/261706571071.webp",
      "page_url": "https://eyecannndy.com/technique/trucking",
      "discovered_at": "2025-09-09T08:56:27.560936",
      "element_tag": "img",
      "title": "Absolut - The Walk",
      "description": "",
      "category": "Technique",
      "alt_text": "Absolut - The Walk",
      "css_classes": "lazy-img lazyImages1 trigger_info_",
      "file_size": null,
      "dimensions": null,
      "tags": [
        "Eyecandy",
        "lazy img",
        "trigger_info_",
        "lazyImages1"
      ]
    },
    {
      "video_url": "https://asset.eyecannndy.com/media/clip/2024/02/28/261709097934.webp",
      "page_url": "https://eyecannndy.com/technique/trucking",
      "discovered_at": "2025-09-09T08:56:27.560973",
      "element_tag": "img",
      "title": "Beethoven",
      "description": "",
      "category": "Technique",
      "alt_text": "Beethoven",
      "css_classes": "lazy-img lazyImages1 trigger_info_",
      "file_size": null,
      "dimensions": null,
      "tags": [
        "Eyecandy",
        "lazy img",
        "trigger_info_",
        "lazyImages1"
      ]
    },
    {
      "video_url": "https://asset.eyecannndy.com/media/clip/2024/03/25/261711344573.webp",
      "page_url": "https://eyecannndy.com/technique/trucking",
      "discovered_at": "2025-09-09T08:56:27.561009",
      "element_tag": "img",
      "title": "Fantastic Mr. Fox",
      "description": "",
      "category": "Technique",
      "alt_text": "Fantastic Mr. Fox",
      "css_classes": "lazy-img lazyImages1 trigger_info_",
      "file_size": null,
      "dimensions": null,
      "tags": [
        "Eyecandy",
        "lazy img",
        "trigger_info_",
        "lazyImages1"
      ]
    },
    {
      "video_url": "https://asset.eyecannndy.com/media/clip/2023/12/20/261703056102.webp",
      "page_url": "https://eyecannndy.com/technique/trucking",
      "discovered_at": "2025-09-09T08:56:27.561046",
      "element_tag": "img",
      "title": "Barbie",
      "description": "",
      "category": "Technique",
      "alt_text": "Barbie",
      "css_classes": "lazy-img lazyImages1 trigger_info_",
      "file_size": null,
      "dimensions": null,
      "tags": [
        "Eyecandy",
        "lazy img",
        "trigger_info_",
        "lazyImages1"
      ]
    },
    {
      "video_url": "https://asset.eyecannndy.com/media/clip/2023/12/20/261703056041.webp",
      "page_url": "https://eyecannndy.com/technique/trucking",
      "discovered_at": "2025-09-09T08:56:27.561083",
      "element_tag": "img",
      "title": "Barbie",
      "description": "",
      "category": "Technique",
      "alt_text": "Barbie",
      "css_classes": "lazy-img lazyImages1 trigger_info_",
      "file_size": null,
      "dimensions": null,
      "tags": [
        "Eyecandy",
        "lazy img",
        "trigger_info_",
        "lazyImages1"
      ]
    }
  ]
}